etraxx.py
xpfx_pypi_playground-0.0.2.dist-info/METADATA
xpfx_pypi_playground-0.0.2.dist-info/WHEEL
xpfx_pypi_playground-0.0.2.dist-info/top_level.txt
xpfx_pypi_playground-0.0.2.dist-info/RECORD
