Metadata-Version: 2.4
Name: xpfx.pypi.playground
Version: 0.0.2
Summary: Just a simple Playground File for playing around :-D
Requires-Python: >=3.12
